agilize/__init__.py
agilize/agilize.py
agilize/client.py
agilize/keycloak.py
Agilize-0.0.4.dist-info/LICENSE
Agilize-0.0.4.dist-info/METADATA
Agilize-0.0.4.dist-info/WHEEL
Agilize-0.0.4.dist-info/top_level.txt
Agilize-0.0.4.dist-info/RECORD
