Metadata-Version: 2.1
Name: Agilize
Version: 0.0.4
Summary: Unofficial client to access Agilize
Home-page: https://github.com/lucasrcezimbra/agilize
Author: Lucas Rangel Cezimbra
Author-email: lucas@cezimbra.tec.br
License: LGPLv2
Keywords: agilize,api,client,requests,accounting,finance
Classifier: Development Status :: 4 - Beta
Classifier: Intended Audience :: Developers
Classifier: License :: OSI Approved :: GNU Lesser General Public License v2 (LGPLv2)
Classifier: Programming Language :: Python :: 3
Classifier: Programming Language :: Python :: 3 :: Only
Classifier: Programming Language :: Python :: Implementation :: CPython
Classifier: Topic :: Office/Business :: Financial
Classifier: Topic :: Office/Business :: Financial :: Accounting
License-File: LICENSE
Requires-Dist: attrs
Requires-Dist: requests
